clabe/__init__.py
clabe/_typing.py
clabe/apps/__init__.py
clabe/apps/_base.py
clabe/apps/_bonsai.py
clabe/apps/_curriculum.py
clabe/apps/_executors.py
clabe/apps/_python_script.py
clabe/apps/open_ephys.py
clabe/cache_manager.py
clabe/cli.py
clabe/constants.py
clabe/data_mapper/__init__.py
clabe/data_mapper/_base.py
clabe/data_mapper/aind_data_schema.py
clabe/data_mapper/helpers.py
clabe/data_transfer/__init__.py
clabe/data_transfer/_base.py
clabe/data_transfer/aind_watchdog.py
clabe/data_transfer/robocopy.py
clabe/git_manager/__init__.py
clabe/git_manager/_git.py
clabe/launcher/__init__.py
clabe/launcher/_base.py
clabe/launcher/_cli.py
clabe/launcher/_experiments.py
clabe/logging_helper/__init__.py
clabe/logging_helper/_stdlib.py
clabe/logging_helper/aibs.py
clabe/pickers/__init__.py
clabe/pickers/_by_animal_modifier.py
clabe/pickers/dataverse.py
clabe/pickers/default_behavior.py
clabe/py.typed
clabe/resource_monitor/__init__.py
clabe/resource_monitor/_base.py
clabe/resource_monitor/_constraints.py
clabe/services.py
clabe/ui/__init__.py
clabe/ui/questionary_ui_helper.py
clabe/ui/ui_helper.py
clabe/utils/__init__.py
clabe/utils/aind_auth.py
clabe/utils/keepass.py
clabe/xml_rpc/__init__.py
clabe/xml_rpc/_client.py
clabe/xml_rpc/_executor.py
clabe/xml_rpc/_server.py
clabe/xml_rpc/models.py
aind_clabe-0.10.0.dist-info/licenses/LICENSE
aind_clabe-0.10.0.dist-info/WHEEL
aind_clabe-0.10.0.dist-info/entry_points.txt
aind_clabe-0.10.0.dist-info/METADATA
aind_clabe-0.10.0.dist-info/RECORD
