Metadata-Version: 2.4
Name: aind-clabe
Version: 0.10.0
Summary: A library for a minimal framework that can be used to build experimental interfaces.
Author: Bruno Cruz
Author-email: Bruno Cruz <bruno.cruz@alleninstitute.org>
License-Expression: MIT
License-File: LICENSE
Classifier: Programming Language :: Python :: 3.11
Classifier: Programming Language :: Python :: 3.12
Classifier: Programming Language :: Python :: 3.13
Classifier: Operating System :: Microsoft :: Windows
Requires-Dist: pydantic>=2.7
Requires-Dist: pydantic-settings
Requires-Dist: gitpython
Requires-Dist: requests
Requires-Dist: semver
Requires-Dist: rich
Requires-Dist: questionary
Requires-Dist: aind-behavior-services>=0.13.0
Requires-Dist: requests ; extra == 'aind-services'
Requires-Dist: pyyaml ; extra == 'aind-services'
Requires-Dist: pykeepass ; extra == 'aind-services'
Requires-Dist: ms-active-directory ; extra == 'aind-services'
Requires-Dist: cryptography ; extra == 'aind-services'
Requires-Dist: winkerberos ; sys_platform == 'win32' and extra == 'aind-services'
Requires-Dist: ldap3 ; sys_platform == 'win32' and extra == 'aind-services'
Requires-Dist: msal ; sys_platform == 'win32' and extra == 'aind-services'
Requires-Dist: aind-data-schema>=2 ; extra == 'aind-services'
Requires-Dist: aind-data-transfer-service>=1.22.0 ; extra == 'aind-services'
Requires-Dist: aind-watchdog-service>=0.1.6 ; extra == 'aind-services'
Requires-Python: >=3.11
Project-URL: Documentation, https://allenneuraldynamics.github.io/clabe/
Project-URL: Repository, https://github.com/AllenNeuralDynamics/clabe/
Project-URL: Issues, https://github.com/AllenNeuralDynamics/clabe/issues
Project-URL: Changelog, https://github.com/AllenNeuralDynamics/clabe/releases
Provides-Extra: aind-services
